nr/__init__.py
nr/interface.py
nr.interface-0.0.5.dist-info/LICENSE.txt
nr.interface-0.0.5.dist-info/METADATA
nr.interface-0.0.5.dist-info/WHEEL
nr.interface-0.0.5.dist-info/top_level.txt
nr.interface-0.0.5.dist-info/zip-safe
nr.interface-0.0.5.dist-info/RECORD
