Metadata-Version: 2.1
Name: nr.interface
Version: 0.0.5
Summary: Interface definitions for Python.
Home-page: https://git.niklasrosenstein.com/NiklasRosenstein/nr
Author: Niklas Rosenstein
Author-email: rosensteinniklas@gmail.com
License: MIT
Platform: UNKNOWN
Requires-Dist: nr.collections (<1.0.0,>=0.0.1)
Requires-Dist: nr.metaclass (<0.1.0,>=0.0.1)
Requires-Dist: nr.pylang.utils (<0.1.0,>=0.0.1)
Requires-Dist: six (<2.0.0,>=1.11.0)
